{
  "db_name": "PostgreSQL",
  "query": "\n        SELECT map_id, owner_account_id, name, created_at,\n               last_checkpoint_seq, last_checkpoint_at, retention_days\n        FROM maps\n        WHERE owner_account_id = $1\n        ORDER BY created_at ASC\n        ",
  "describe": {
    "columns": [
      {
        "ordinal": 0,
        "name": "map_id",
        "type_info": "Uuid"
      },
      {
        "ordinal": 1,
        "name": "owner_account_id",
        "type_info": "Uuid"
      },
      {
        "ordinal": 2,
        "name": "name",
        "type_info": "Text"
      },
      {
        "ordinal": 3,
        "name": "created_at",
        "type_info": "Timestamptz"
      },
      {
        "ordinal": 4,
        "name": "last_checkpoint_seq",
        "type_info": "Int8"
      },
      {
        "ordinal": 5,
        "name": "last_checkpoint_at",
        "type_info": "Timestamptz"
      },
      {
        "ordinal": 6,
        "name": "retention_days",
        "type_info": "Int4"
      }
    ],
    "parameters": {
      "Left": [
        "Uuid"
      ]
    },
    "nullable": [
      false,
      false,
      false,
      false,
      false,
      true,
      false
    ]
  },
  "hash": "046f67e0b517995d76648da77f821814f0aa35fb703facafa6aa6ea4c6ef50bd"
}
